rico-0.4.0.dist-info/METADATA
rico-0.4.0.dist-info/WHEEL
rico-0.4.0.dist-info/licenses/LICENSE
rico/__init__.py
rico/_config.py
rico/_container.py
rico/_content.py
rico/_html.py
rico/_version.py
rico/_version.txt
rico-0.4.0.dist-info/RECORD
